flit_callable/__init__.py
flit_callable/bar.py
flit_callable/flit_callable.py
flit_callable-0.3.1.dist-info/LICENSE
flit_callable-0.3.1.dist-info/WHEEL
flit_callable-0.3.1.dist-info/METADATA
flit_callable-0.3.1.dist-info/RECORD
