Metadata-Version: 2.1
Name: flit_callable
Version: 0.3.1
Summary: Flit callable in package
Home-page: https://github.com
License: UNKNOWN
Author: xichen3
Author-email: xichen3@microsoft.com
Classifier: License :: OSI Approved :: MIT License
